bussess/__init__.py
bussess/admin.py
bussess/apps.py
bussess/models.py
bussess/tests.py
bussess/urls.py
bussess/views.py
bussess/migrations/__init__.py
myapp/__init__.py
myapp/admin.py
myapp/apps.py
myapp/models.py
myapp/tests.py
myapp/urls.py
myapp/views.py
myapp/migrations/0001_initial.py
myapp/migrations/__init__.py
waimai/__init__.py
waimai/settings.py
waimai/urls.py
waimai/wsgi.py
yindd-1.0.0.dist-info/METADATA
yindd-1.0.0.dist-info/WHEEL
yindd-1.0.0.dist-info/top_level.txt
yindd-1.0.0.dist-info/RECORD
